gauss_binomial_statdist/Binomialdistribution.py
gauss_binomial_statdist/Gaussiandistribution.py
gauss_binomial_statdist/Generaldistribution.py
gauss_binomial_statdist/__init__.py
gauss_binomial_statdist-0.0.3.dist-info/LICENSE
gauss_binomial_statdist-0.0.3.dist-info/METADATA
gauss_binomial_statdist-0.0.3.dist-info/WHEEL
gauss_binomial_statdist-0.0.3.dist-info/top_level.txt
gauss_binomial_statdist-0.0.3.dist-info/RECORD
