Metadata-Version: 2.1
Name: gauss-binomial-statdist
Version: 0.0.3
Summary: Code to enable the use of the gaussian and the binomial distributions
Author: Oumayma EL-FAHSI
Author-email: <oumayma.elfahsi@ump.ac.ma>
Keywords: python,gaussian,binomial,distributions,mean,standard deviation,statistics
Classifier: Intended Audience :: Developers
Classifier: Programming Language :: Python :: 3
License-File: LICENSE
Requires-Dist: matplotlib
